pkgmgr/__init__.py
pkgmgr/__main__.py
pkgmgr/cli.py
pkgmgr/config.py
pkgmgr/gitcollect.py
pkgmgr/points.py
pkgmgr/release.py
pkgmgr/shell_integration.py
pkgmgr/snapshot.py
pkgmgr/watch.py
pkgmgr/collectors/__init__.py
pkgmgr/collectors/base.py
pkgmgr/collectors/checksums.py
pkgmgr/templates/pkg.yaml.sample
pkgmgr/templates/pkgmgr.yaml.sample
pkgmgr_kunrunic-0.1.1.dev1.dist-info/licenses/LICENSE
pkgmgr_kunrunic-0.1.1.dev1.dist-info/METADATA
pkgmgr_kunrunic-0.1.1.dev1.dist-info/WHEEL
pkgmgr_kunrunic-0.1.1.dev1.dist-info/entry_points.txt
pkgmgr_kunrunic-0.1.1.dev1.dist-info/top_level.txt
pkgmgr_kunrunic-0.1.1.dev1.dist-info/RECORD
