Metadata-Version: 2.4
Name: pkgmgr-kunrunic
Version: 0.1.1.dev1
Summary: Package management workflow scaffold.
Author: pkgmgr maintainers
License: MIT License
Project-URL: Homepage, https://github.com/kunrunic/pkgmgnt
Project-URL: Repository, https://github.com/kunrunic/pkgmgnt
Classifier: Development Status :: 2 - Pre-Alpha
Classifier: Intended Audience :: Developers
Classifier: License :: OSI Approved :: MIT License
Classifier: Environment :: Console
Classifier: Programming Language :: Python
Classifier: Programming Language :: Python :: 3
Classifier: Programming Language :: Python :: 3 :: Only
Classifier: Programming Language :: Python :: 3.6
Classifier: Programming Language :: Python :: 3.7
Classifier: Programming Language :: Python :: 3.8
Classifier: Programming Language :: Python :: 3.9
Classifier: Programming Language :: Python :: 3.10
Classifier: Programming Language :: Python :: 3.11
Classifier: Programming Language :: Python :: 3.12
Classifier: Topic :: Software Development :: Build Tools
Requires-Python: >=3.6
License-File: LICENSE
Requires-Dist: pyyaml>=6.0
Dynamic: license-file
